ModuBotDiscord/__init__.py
ModuBotDiscord/checks/owner/__init__.py
ModuBotDiscord/checks/owner/check.py
ModuBotDiscord/checks/permissions/__init__.py
ModuBotDiscord/checks/permissions/check.py
ModuBotDiscord/checks/permissions/enum.py
ModuBotDiscord/commands/__init__.py
ModuBotDiscord/config/__init__.py
ModuBotDiscord/config/discord.py
ModuBotDiscord/enums/__init__.py
ModuBotDiscord/enums/permission.py
ModuBotDiscord/utils/enums.py
ModuBotDiscord/utils/messages.py
modubotdiscord-0.5.1.dist-info/licenses/LICENSE
modubotdiscord-0.5.1.dist-info/METADATA
modubotdiscord-0.5.1.dist-info/WHEEL
modubotdiscord-0.5.1.dist-info/top_level.txt
modubotdiscord-0.5.1.dist-info/RECORD
