Metadata-Version: 2.4
Name: ModuBotDiscord
Version: 0.5.1
Summary: Modular Discord bot framework built on top of ModuBotCore
Author-email: Endkind <endkind.ender@endkind.net>
Project-URL: Source, https://github.com/EnderModuBot/discord
Requires-Python: >=3.9
License-File: LICENSE
Requires-Dist: ModuBotCore>=0.0.3
Requires-Dist: discord.py>=2.5.2
Dynamic: license-file
